rosetree/__init__.py
rosetree/draw.py
rosetree/tree.py
rosetree/trie.py
rosetree/utils.py
rosetree/weighted.py
rosetree-0.2.0.dist-info/METADATA
rosetree-0.2.0.dist-info/WHEEL
rosetree-0.2.0.dist-info/licenses/LICENSE
rosetree-0.2.0.dist-info/RECORD
