Metadata-Version: 2.4
Name: rosetree
Version: 0.2.0
Summary: Generic tree data structure.
Project-URL: Documentation, https://github.com/jeremander/rosetree#readme
Project-URL: Issues, https://github.com/jeremander/rosetree/issues
Project-URL: Source, https://github.com/jeremander/rosetree
Author-email: Jeremy Silver <jeremys@nessiness.com>
License: MIT License
License-File: LICENSE
Classifier: Programming Language :: Python
Requires-Python: >=3.9
Requires-Dist: typing-extensions>=4.10
Provides-Extra: draw
Requires-Dist: kaleido; extra == 'draw'
Requires-Dist: matplotlib; extra == 'draw'
Requires-Dist: networkx; extra == 'draw'
Requires-Dist: plotly; extra == 'draw'
